_accelerated_sequence_clustering.cpython-38-x86_64-linux-gnu.so
accelerated_sequence_clustering.py
accelerated_sequence_clustering-1.0.2.dist-info/WHEEL
accelerated_sequence_clustering-1.0.2.dist-info/RECORD
accelerated_sequence_clustering-1.0.2.dist-info/top_level.txt
accelerated_sequence_clustering-1.0.2.dist-info/LICENSE
accelerated_sequence_clustering-1.0.2.dist-info/METADATA
