Metadata-Version: 2.1
Name: accelerated-sequence-clustering
Version: 1.0.2
Summary: Fast sequence clustering module
Author: Reza Mortazavi
Author-email: Reza Mortazavi <ir1979@gmail.com>
License: MIT License
Project-URL: Homepage, https://github.com/ir1979/ASCM
Keywords: sequence,data clustering,grouping
Classifier: License :: OSI Approved :: MIT License
Classifier: Programming Language :: Python
Classifier: Programming Language :: Python :: 3
Requires-Python: >=3.8
License-File: LICENSE
